[
  {
    "experiment": "a3_e3_multiheavy_path_reranker_ood_branching3_round4_eval",
    "stage": "scout",
    "bucket": "exploit",
    "notes": "round4 OOD stress for the combined multiheavy plus path-reranker exploit leader on higher branching and queue load",
    "device": "cuda:0",
    "num_communities": 4,
    "tree_depth_min": 2,
    "tree_depth_max": 3,
    "branching_factor": 3,
    "packets_max": 6,
    "queue_low": 1.5,
    "queue_high": 7.0,
    "queue_penalty": 0.35,
    "capacity_penalty": 2.5,
    "urgency_penalty": 1.2,
    "decision_loss": 2.532344188871263,
    "test_next_hop_accuracy": 0.964135039456283,
    "value_mae": 2.5607349540613873,
    "value_rmse": 3.2778642343569406,
    "rollout_solved_rate": 1.0,
    "rollout_next_hop_accuracy": 0.9351669941060904,
    "average_regret": 4.985918045043945,
    "p95_regret": 12.641508102416992,
    "worst_regret": 20.582395553588867,
    "deadline_violations": 2.3125,
    "deadline_miss_rate": 1.0,
    "p95_deadline_violations": 4.0,
    "priority_delivered_regret": 1.625
  },
  {
    "experiment": "a3_e3_multiheavy_path_reranker_ood_deeper_packets6_round4_eval",
    "stage": "scout",
    "bucket": "exploit",
    "notes": "round4 OOD stress for the combined multiheavy plus path-reranker exploit leader on deeper trees and more packets",
    "device": "cuda:0",
    "num_communities": 4,
    "tree_depth_min": 3,
    "tree_depth_max": 4,
    "branching_factor": 2,
    "packets_max": 6,
    "queue_low": 1.0,
    "queue_high": 6.0,
    "queue_penalty": 0.35,
    "capacity_penalty": 2.5,
    "urgency_penalty": 1.2,
    "decision_loss": 7.1096755978133945,
    "test_next_hop_accuracy": 0.9657118055555556,
    "value_mae": 4.287101892961396,
    "value_rmse": 5.635690874523586,
    "rollout_solved_rate": 1.0,
    "rollout_next_hop_accuracy": 0.9586466165413534,
    "average_regret": 3.4164037704467773,
    "p95_regret": 9.192599296569824,
    "worst_regret": 9.273791313171387,
    "deadline_violations": 1.375,
    "deadline_miss_rate": 0.875,
    "p95_deadline_violations": 3.0,
    "priority_delivered_regret": 0.6875
  },
  {
    "experiment": "a3_e3_multiheavy_path_reranker_ood_heavy_dynamic_round4_eval",
    "stage": "scout",
    "bucket": "exploit",
    "notes": "round4 OOD stress for the combined multiheavy plus path-reranker exploit leader on deeper queues and stronger congestion penalties",
    "device": "cuda:0",
    "num_communities": 4,
    "tree_depth_min": 3,
    "tree_depth_max": 4,
    "branching_factor": 2,
    "packets_max": 8,
    "queue_low": 2.5,
    "queue_high": 8.0,
    "queue_penalty": 0.45,
    "capacity_penalty": 3.0,
    "urgency_penalty": 1.4,
    "decision_loss": 35.24103682327271,
    "test_next_hop_accuracy": 0.9700000200271607,
    "value_mae": 10.699622604370116,
    "value_rmse": 12.928398937225342,
    "rollout_solved_rate": 1.0,
    "rollout_next_hop_accuracy": 0.953360768175583,
    "average_regret": 5.072554111480713,
    "p95_regret": 13.216791152954102,
    "worst_regret": 15.489541053771973,
    "deadline_violations": 2.5625,
    "deadline_miss_rate": 0.9375,
    "p95_deadline_violations": 5.25,
    "priority_delivered_regret": 1.1875
  }
]